fastcord/__init__.py
fastcord/__main__.py
fastcord/_types.py
fastcord/abc.py
fastcord/activity.py
fastcord/appinfo.py
fastcord/asset.py
fastcord/audit_logs.py
fastcord/automod.py
fastcord/backoff.py
fastcord/channel.py
fastcord/client.py
fastcord/colour.py
fastcord/components.py
fastcord/context_managers.py
fastcord/embeds.py
fastcord/emoji.py
fastcord/enums.py
fastcord/errors.py
fastcord/file.py
fastcord/flags.py
fastcord/gateway.py
fastcord/guild.py
fastcord/http.py
fastcord/integrations.py
fastcord/interactions.py
fastcord/invite.py
fastcord/member.py
fastcord/mentions.py
fastcord/message.py
fastcord/mixins.py
fastcord/object.py
fastcord/oggparse.py
fastcord/opus.py
fastcord/partial_emoji.py
fastcord/permissions.py
fastcord/player.py
fastcord/py.typed
fastcord/raw_models.py
fastcord/reaction.py
fastcord/role.py
fastcord/scheduled_event.py
fastcord/shard.py
fastcord/sku.py
fastcord/stage_instance.py
fastcord/state.py
fastcord/sticker.py
fastcord/team.py
fastcord/template.py
fastcord/threads.py
fastcord/user.py
fastcord/utils.py
fastcord/voice_client.py
fastcord/voice_state.py
fastcord/welcome_screen.py
fastcord/widget.py
fastcord/app_commands/__init__.py
fastcord/app_commands/checks.py
fastcord/app_commands/commands.py
fastcord/app_commands/errors.py
fastcord/app_commands/models.py
fastcord/app_commands/namespace.py
fastcord/app_commands/transformers.py
fastcord/app_commands/translator.py
fastcord/app_commands/tree.py
fastcord/ext/commands/__init__.py
fastcord/ext/commands/_types.py
fastcord/ext/commands/bot.py
fastcord/ext/commands/cog.py
fastcord/ext/commands/context.py
fastcord/ext/commands/converter.py
fastcord/ext/commands/cooldowns.py
fastcord/ext/commands/core.py
fastcord/ext/commands/errors.py
fastcord/ext/commands/flags.py
fastcord/ext/commands/help.py
fastcord/ext/commands/hybrid.py
fastcord/ext/commands/parameters.py
fastcord/ext/commands/view.py
fastcord/ext/tasks/__init__.py
fastcord/types/__init__.py
fastcord/types/activity.py
fastcord.py-2.4.0a0.dist-info/LICENSE
fastcord.py-2.4.0a0.dist-info/METADATA
fastcord.py-2.4.0a0.dist-info/WHEEL
fastcord.py-2.4.0a0.dist-info/top_level.txt
fastcord.py-2.4.0a0.dist-info/RECORD
